trier/__init__.py
trier-1.0.6.dist-info/LICENSE
trier-1.0.6.dist-info/WHEEL
trier-1.0.6.dist-info/METADATA
trier-1.0.6.dist-info/RECORD
