Metadata-Version: 2.1
Name: trier
Version: 1.0.6
Summary: Utility wrapper to handle exceptions.
Home-page: https://github.com/omegatrix/trier
License: MIT
Keywords: error-handling,python3,async-await,try-except,try-catch
Author: Arnold Anthonypillai
Author-email: arnoldbronson16@gmail.com
Requires-Python: >=3.8,<4.0
Classifier: Development Status :: 5 - Production/Stable
Classifier: Intended Audience :: Developers
Classifier: License :: OSI Approved :: MIT License
Classifier: Operating System :: OS Independent
Classifier: Programming Language :: Python :: 3
Classifier: Programming Language :: Python :: 3.10
Classifier: Programming Language :: Python :: 3.8
Classifier: Programming Language :: Python :: 3.9
Classifier: Topic :: Software Development
Classifier: Topic :: Utilities
Classifier: Typing :: Typed
Project-URL: Repository, https://github.com/omegatrix/trier
